admin_methods/__init__.py
admin_methods/actions.py
admin_methods/exceptions.py
admin_methods/list.py
admin_methods/model.py
admin_methods/templates/__init__.py
admin_methods/templates/admin_methods/__init__.py
admin_methods/templates/admin_methods/list/__init__.py
admin_methods/templates/admin_methods/list/toggle.html
admin_methods/templates/admin_methods/model/__init__.py
admin_methods/templates/admin_methods/model/image_thumb.html
django_admin_methods-0.1.13.dist-info/DESCRIPTION.rst
django_admin_methods-0.1.13.dist-info/entry_points.txt
django_admin_methods-0.1.13.dist-info/METADATA
django_admin_methods-0.1.13.dist-info/metadata.json
django_admin_methods-0.1.13.dist-info/RECORD
django_admin_methods-0.1.13.dist-info/top_level.txt
django_admin_methods-0.1.13.dist-info/WHEEL
