Metadata-Version: 2.0
Name: django-admin-methods
Version: 0.1.13
Summary: Quickly create admin related actions, list properties and single instance properties for Django
Home-page: https://github.com/matiboy/django-admin-methods.git
Author: Matiboy
Author-email: mathieu@redapesolutions.com
License: MIT
Keywords: django admin actions fields
Platform: UNKNOWN
Classifier: Development Status :: 4 - Beta
Classifier: Intended Audience :: Developers
Classifier: Framework :: Django
Classifier: License :: OSI Approved :: MIT License
Classifier: Programming Language :: Python :: 2
Classifier: Programming Language :: Python :: 2.6
Classifier: Programming Language :: Python :: 2.7
Classifier: Programming Language :: Python :: 3
Classifier: Programming Language :: Python :: 3.2
Classifier: Programming Language :: Python :: 3.3
Classifier: Programming Language :: Python :: 3.4
Requires-Dist: html2text
Provides-Extra: dev
Requires-Dist: check-manifest; extra == 'dev'
Provides-Extra: test
Requires-Dist: coverage; extra == 'test'
